Metadata-Version: 2.0
Name: odoo9-addon-procurement-operating-unit
Version: 9.0.1.0.0
Summary: An operating unit (OU) is an organizational entity part of a company
Home-page: http://www.eficent.com
Author: Eficent, Serpent Consulting Services Pvt. Ltd., Odoo Community Association (OCA)
Author-email: support@odoo-community.org
License: LGPL-3
Platform: UNKNOWN
Requires-Dist: odoo (<9.1a,>=9.0a)
Requires-Dist: odoo9-addon-operating-unit
Requires-Dist: odoo9-addon-stock-operating-unit
Classifier: Programming Language :: Python :: 2.7
Classifier: Framework :: Odoo
Classifier: License :: OSI Approved :: GNU Lesser General Public License v3 (LGPLv3)
